Metadata-Version: 1.0
Name: distributions-pranav
Version: 0.1
Summary: Gaussian distributions
Home-page: UNKNOWN
Author: UNKNOWN
Author-email: nspranav1180@gmail.com
License: UNKNOWN
Platform: UNKNOWN
